sms_gateway/__init__.py
sms_gateway/__main__.py
sms_gateway/config.py
sms_gateway/background_threads/__init__.py
sms_gateway/background_threads/sms_sender.py
sms_gateway/controllers/__init__.py
sms_gateway/controllers/controller_utils.py
sms_gateway/controllers/sms.py
sms_gateway-0.1.9.dist-info/LICENSE
sms_gateway-0.1.9.dist-info/METADATA
sms_gateway-0.1.9.dist-info/WHEEL
sms_gateway-0.1.9.dist-info/entry_points.txt
sms_gateway-0.1.9.dist-info/top_level.txt
sms_gateway-0.1.9.dist-info/RECORD
