Metadata-Version: 2.1
Name: sms-gateway
Version: 0.1.9
Summary: Web App Serving as an SMS Gateway based on Gammu
Home-page: https://github.com/joneug/sms-gateway
Author: joneug
License: MIT
Project-URL: Documentation, https://github.com/joneug/sms-gateway
Project-URL: Source, https://github.com/joneug/sms-gateway
Project-URL: Tracker, https://github.com/joneug/sms-gateway/issues
Keywords: SMS,gateway,gammu
Platform: UNKNOWN
Classifier: Programming Language :: Python :: 3
Classifier: Programming Language :: Python :: 3.5
Classifier: Programming Language :: Python :: 3.6
Classifier: Programming Language :: Python :: 3.7
Classifier: Programming Language :: Python :: 3.8
Classifier: Programming Language :: Python :: 3.9
Classifier: Environment :: Console
Classifier: Operating System :: MacOS :: MacOS X
Classifier: Operating System :: Microsoft :: Windows
Classifier: Operating System :: POSIX :: Linux
Requires-Python: >= 3.5
Requires-Dist: falcon (>=2.0.0)
Requires-Dist: falcon-auth (>=1.1.0)
Requires-Dist: python-gammu (>=3.1)
